README.md
setup.py
bin/kreta
kreta/__init__.py
kreta/__main__.py
kreta/api.py
kreta/core.py
kreta/utils.py
kreta.egg-info/PKG-INFO
kreta.egg-info/SOURCES.txt
kreta.egg-info/dependency_links.txt
kreta.egg-info/top_level.txt