Metadata-Version: 1.1
Name: kreta
Version: 0.0.9
Summary: KRÉTA Ellenörző CLI
Home-page: https://github.com/UnknownPlayer78/kreta-cli
Author: UnknownPlayer78
Author-email: UNKNOWN
License: MIT
Keywords: e-kreta kreta cli kreta-cli
Platform: UNKNOWN
Classifier: License :: OSI Approved :: MIT License
Classifier: Programming Language :: Python :: 3
